{
    "modelo": "ArticulosNew",
    "namespace": "Produccion",
    "carpeta_vistas": "produccion\/abms\/articulos_new",
    "timestamps": "1",
    "sincronizable": "1",
    "force_controlador": true,
    "primary_key": "id",
    "primary_key_sql": [
        "cod_articulo"
    ],
    "indices": {
        "idx_unico_cod_articulo": {
            "columns": [
                "cod_articulo"
            ],
            "unique": true
        }
    },
    "campos": {
        "cod_articulo": {
            "label": "Code",
            "default": null,
            "input_type": "text",
            "incluir": true,
            "nullable": false,
            "select_list_data": null,
            "referenced_table": null,
            "referenced_column": "id",
            "referenced_label": "nombre",
            "is_boolean": false,
            "auto_increment_plus": false,
            "sync": "1"
        },
        "denom_articulo": {
            "label": "nombre",
            "default": null,
            "input_type": "text",
            "incluir": true,
            "nullable": false,
            "select_list_data": null,
            "referenced_table": null,
            "referenced_column": "id",
            "referenced_label": "nombre",
            "is_boolean": false,
            "auto_increment_plus": false,
            "sync": "1"
        },
        "descripcion_larga": {
            "label": "Descripcion",
            "default": null,
            "input_type": "textarea",
            "incluir": true,
            "nullable": false,
            "select_list_data": null,
            "referenced_table": null,
            "referenced_column": "id",
            "referenced_label": "nombre",
            "is_boolean": false,
            "auto_increment_plus": false,
            "sync": "1"
        },
        "precio_unitario": {
            "label": "Precio",
            "default": null,
            "input_type": "moneda",
            "incluir": true,
            "nullable": false,
            "select_list_data": null,
            "referenced_table": null,
            "referenced_column": "id",
            "referenced_label": "nombre",
            "is_boolean": false,
            "auto_increment_plus": false,
            "sync": "1"
        },
        "cantidad_stock": {
            "label": "Cantidad stock",
            "default": null,
            "input_type": "number",
            "incluir": true,
            "nullable": false,
            "select_list_data": null,
            "referenced_table": null,
            "referenced_column": "id",
            "referenced_label": "nombre",
            "is_boolean": false,
            "auto_increment_plus": false,
            "sync": "1"
        },
        "disponible": {
            "label": "Disponible",
            "default": null,
            "input_type": "checkbox",
            "incluir": true,
            "nullable": false,
            "select_list_data": "Si=S,No=N",
            "referenced_table": null,
            "referenced_column": "id",
            "referenced_label": "nombre",
            "is_boolean": true,
            "auto_increment_plus": false,
            "sync": "1",
            "checkbox_checked_value": "S",
            "checkbox_unchecked_value": "N"
        },
        "tipo_articulo": {
            "label": "Tipo articulo",
            "default": null,
            "input_type": "select",
            "incluir": true,
            "nullable": false,
            "select_list_data": null,
            "referenced_table": "familias_producto",
            "referenced_column": "id",
            "referenced_label": "nombre",
            "is_boolean": false,
            "auto_increment_plus": false,
            "sync": "1"
        },
        "categoria_id": {
            "label": "Categoria id",
            "default": null,
            "input_type": "select_list",
            "incluir": true,
            "nullable": false,
            "select_list_data": "Mprima=1, producto=2,Otros=3",
            "referenced_table": null,
            "referenced_column": "id",
            "referenced_label": "nombre",
            "is_boolean": false,
            "auto_increment_plus": false,
            "sync": "1"
        },
        "fecha_lanzamiento": {
            "label": "Fecha lanzamiento",
            "default": null,
            "input_type": "date",
            "incluir": true,
            "nullable": false,
            "select_list_data": null,
            "referenced_table": null,
            "referenced_column": "id",
            "referenced_label": "nombre",
            "is_boolean": false,
            "auto_increment_plus": false,
            "sync": "1"
        },
        "email_contacto": {
            "label": "Email contacto",
            "default": null,
            "input_type": "email",
            "incluir": true,
            "nullable": false,
            "select_list_data": null,
            "referenced_table": null,
            "referenced_column": "id",
            "referenced_label": "nombre",
            "is_boolean": false,
            "auto_increment_plus": false,
            "sync": "1"
        },
        "url_manual": {
            "label": "Url manual",
            "default": null,
            "input_type": "url",
            "incluir": true,
            "nullable": false,
            "select_list_data": null,
            "referenced_table": null,
            "referenced_column": "id",
            "referenced_label": "nombre",
            "is_boolean": false,
            "auto_increment_plus": false,
            "sync": "1"
        },
        "color_preferido": {
            "label": "Color preferido",
            "default": null,
            "input_type": "select_list",
            "incluir": true,
            "nullable": false,
            "select_list_data": "gris,negro,rojo",
            "referenced_table": null,
            "referenced_column": "id",
            "referenced_label": "nombre",
            "is_boolean": false,
            "auto_increment_plus": false,
            "sync": "1"
        },
        "telefono_fabrica": {
            "label": "Telefono fabrica",
            "default": null,
            "input_type": "tel",
            "incluir": true,
            "nullable": false,
            "select_list_data": null,
            "referenced_table": null,
            "referenced_column": "id",
            "referenced_label": "nombre",
            "is_boolean": false,
            "auto_increment_plus": false,
            "sync": "1"
        },
        "archivo_manual": {
            "label": "Archivo manual",
            "default": null,
            "input_type": "file",
            "incluir": true,
            "nullable": false,
            "select_list_data": null,
            "referenced_table": null,
            "referenced_column": "id",
            "referenced_label": "nombre",
            "is_boolean": false,
            "auto_increment_plus": false,
            "sync": "1"
        },
        "indices": {
            "label": "Indices",
            "default": null,
            "input_type": "text",
            "incluir": false,
            "nullable": false,
            "select_list_data": null,
            "referenced_table": null,
            "referenced_column": "id",
            "referenced_label": "nombre",
            "is_boolean": false,
            "auto_increment_plus": false,
            "sync": "0"
        },
        "created_at": {
            "label": "Created at",
            "default": null,
            "input_type": "date",
            "incluir": true,
            "nullable": false,
            "select_list_data": null,
            "referenced_table": null,
            "referenced_column": "id",
            "referenced_label": "nombre",
            "is_boolean": false,
            "auto_increment_plus": false,
            "sync": "1"
        },
        "updated_at": {
            "label": "Updated at",
            "default": null,
            "input_type": "date",
            "incluir": true,
            "nullable": false,
            "select_list_data": null,
            "referenced_table": null,
            "referenced_column": "id",
            "referenced_label": "nombre",
            "is_boolean": false,
            "auto_increment_plus": false,
            "sync": "1"
        },
        "sync_status": {
            "label": "Sync status",
            "default": null,
            "input_type": "text",
            "incluir": true,
            "nullable": false,
            "select_list_data": null,
            "referenced_table": null,
            "referenced_column": "id",
            "referenced_label": "nombre",
            "is_boolean": false,
            "auto_increment_plus": false,
            "sync": "1"
        },
        "id": {
            "label": "Id",
            "default": null,
            "input_type": "text",
            "incluir": true,
            "nullable": false,
            "select_list_data": null,
            "referenced_table": null,
            "referenced_column": "id",
            "referenced_label": "nombre",
            "is_boolean": false,
            "auto_increment_plus": false,
            "sync": "0"
        }
    },
    "form_config": {
        "form_name": "ArticulosNew",
        "form_route": "produccion\/abms\/articulos_new",
        "tipo_formulario": "default",
        "usa_paginador": "1",
        "per_page": "100",
        "form_view_type": "modal",
        "index_view_type": "inline"
    },
    "subformularios": []
}